power_daps/__init__.py
power_daps/python3/__init__.py
power_daps/python3/actions/__init__.py
power_daps/python3/actions/clean_action.py
power_daps/python3/actions/default_action.py
power_daps/python3/actions/deps_action.py
power_daps/python3/actions/init_action.py
power_daps/python3/actions/package_action.py
power_daps/python3/actions/run_action.py
power_daps/python3/actions/unit_test_action.py
power_daps/python3/actions/upload_package_action.py
power_daps/python3/templates/__init__.py
power_daps/python3/templates/init/.gitignore
power_daps/python3/templates/init/README.md
power_daps/python3/templates/init/actions.yml
power_daps/python3/templates/init/dependencies.yml
power_daps/python3/templates/init/setup.py
power_daps/python3/templates/init/config/dap_config.yml
power_daps/python3/templates/init/src/PROJECT_NAME/PROJECT_NAME.py
power_daps/python3/templates/init/src/PROJECT_NAME/__init__.py
power_daps/python3/templates/init/test/PROJECT_NAME/test_PROJECT_NAME.py
power_daps_meta_model_python_3-0.0.6.dist-info/METADATA
power_daps_meta_model_python_3-0.0.6.dist-info/WHEEL
power_daps_meta_model_python_3-0.0.6.dist-info/entry_points.txt
power_daps_meta_model_python_3-0.0.6.dist-info/top_level.txt
power_daps_meta_model_python_3-0.0.6.dist-info/RECORD
