Metadata-Version: 2.1
Name: power-daps-meta-model-python-3
Version: 0.0.6
Summary: Python 3 meta-model for power-daps - a build tool that builds apps in multiple languages
Home-page: https://github.com/power-daps/power-daps
Author: Prasanna Pendse
Author-email: prasanna.pendse@gmail.com
License: UNKNOWN
Platform: UNKNOWN
Classifier: Programming Language :: Python :: 3
Classifier: License :: OSI Approved :: GNU General Public License v3 (GPLv3)
Classifier: Operating System :: OS Independent
Requires-Python: >=3.6
